dbyoke/__init__.py
dbyoke/connection.py
dbyoke/connection_string.py
dbyoke/utils.py
dbyoke/drivers/__init__.py
dbyoke/drivers/base.py
dbyoke/drivers/mssql_driver.py
dbyoke/drivers/oracle_driver.py
dbyoke/drivers/postgres_driver.py
dbyoke-0.1.3.dist-info/LICENSE
dbyoke-0.1.3.dist-info/METADATA
dbyoke-0.1.3.dist-info/WHEEL
dbyoke-0.1.3.dist-info/top_level.txt
dbyoke-0.1.3.dist-info/RECORD
