Metadata-Version: 2.1
Name: dbyoke
Version: 0.1.3
Summary: A library to unify database connections and drivers
Home-page: https://github.com/datadev13/dbyoke
Author: datadev13
Author-email: 
License: MIT
Keywords: database connection drivers unification
Classifier: Programming Language :: Python :: 3
Classifier: License :: OSI Approved :: MIT License
Classifier: Operating System :: OS Independent
Classifier: Development Status :: 3 - Alpha
Classifier: Intended Audience :: Developers
Classifier: Topic :: Database
Requires-Python: >=3.10
License-File: LICENSE
Provides-Extra: postgresql
Requires-Dist: psycopg2-binary; extra == "postgresql"
Provides-Extra: mssql
Requires-Dist: pyodbc; extra == "mssql"
Provides-Extra: oracle
Requires-Dist: oracledb; extra == "oracle"
Provides-Extra: all
Requires-Dist: psycopg2-binary; extra == "all"
Requires-Dist: pyodbc; extra == "all"
Requires-Dist: oracledb; extra == "all"
